plumbery/__init__.py
plumbery/__main__.py
plumbery/action.py
plumbery/bootstrap.py
plumbery/engine.py
plumbery/exception.py
plumbery/facility.py
plumbery/fitting.py
plumbery/infrastructure.py
plumbery/nodes.py
plumbery/plogging.py
plumbery/polisher.py
plumbery/terraform.py
plumbery/text.py
plumbery/util.py
plumbery/polishers/__init__.py
plumbery/polishers/ansible.py
plumbery/polishers/backup.py
plumbery/polishers/base.py
plumbery/polishers/configure.py
plumbery/polishers/cpu.py
plumbery/polishers/disks.py
plumbery/polishers/information.py
plumbery/polishers/inventory.py
plumbery/polishers/memory.py
plumbery/polishers/monitoring.py
plumbery/polishers/ping.py
plumbery/polishers/prepare.cloud-init.sh
plumbery/polishers/prepare.docker.sh
plumbery/polishers/prepare.puppet.apache.pp
plumbery/polishers/prepare.puppet.apache.sh
plumbery/polishers/prepare.puppet.mongo-config.pp
plumbery/polishers/prepare.puppet.mongo-mongos.pp
plumbery/polishers/prepare.puppet.mongo-shard.pp
plumbery/polishers/prepare.py
plumbery/polishers/prepare.update.sh
plumbery/polishers/windows.py
plumbery-17.5.22.dist-info/DESCRIPTION.rst
plumbery-17.5.22.dist-info/METADATA
plumbery-17.5.22.dist-info/RECORD
plumbery-17.5.22.dist-info/WHEEL
plumbery-17.5.22.dist-info/entry_points.txt
plumbery-17.5.22.dist-info/metadata.json
plumbery-17.5.22.dist-info/top_level.txt
