Metadata-Version: 2.0
Name: plumbery
Version: 17.5.22
Summary: Cloud automation at Dimension Data with Apache Libcloud
Home-page: https://github.com/DimensionDataCBUSydney/plumbery
Author: Bernard Paques
Author-email: bernard.paques@gmail.com
License: Apache License (2.0)
Keywords: plumbery
Platform: UNKNOWN
Classifier: Development Status :: 4 - Beta
Classifier: Environment :: Console
Classifier: Intended Audience :: Developers
Classifier: Intended Audience :: System Administrators
Classifier: License :: OSI Approved :: Apache Software License
Classifier: Operating System :: OS Independent
Classifier: Programming Language :: Python
Classifier: Topic :: Software Development :: Libraries :: Python Modules
Classifier: Programming Language :: Python :: 2.7
Classifier: Programming Language :: Python :: 3.4
Classifier: Programming Language :: Python :: 3.5
Classifier: Programming Language :: Python :: Implementation :: CPython
Requires-Dist: PyYAML
Requires-Dist: apache-libcloud
Requires-Dist: colorlog
Requires-Dist: netifaces
Requires-Dist: paramiko
Requires-Dist: pywinexe
Requires-Dist: pywinrm
Requires-Dist: requests
Requires-Dist: requests-mock
